PyScalapack/__init__.py
PyScalapack-0.3.17.dist-info/METADATA
PyScalapack-0.3.17.dist-info/WHEEL
PyScalapack-0.3.17.dist-info/top_level.txt
PyScalapack-0.3.17.dist-info/RECORD
