Metadata-Version: 2.1
Name: PyScalapack
Version: 0.3.17
Summary: python wrapper for scalapack
Author-email: Hao Zhang <zh970205@mail.ustc.edu.cn>
License: GPLv3
Project-URL: Homepage, https://github.com/USTC-TNS/TNSP/tree/main/PyScalapack
Project-URL: Repository, https://github.com/USTC-TNS/TNSP.git
Project-URL: Issues, https://github.com/USTC-TNS/TNSP/issues
Project-URL: Changelog, https://github.com/USTC-TNS/TNSP/blob/main/CHANGELOG.org
Keywords: scalapack,lapack,blas,linear algebra,scientific computing,parallel computing,MPI
Classifier: Development Status :: 4 - Beta
Classifier: Programming Language :: Python :: 3
Classifier: License :: OSI Approved :: GNU General Public License v3 or later (GPLv3+)
Classifier: Topic :: Scientific/Engineering :: Mathematics
Classifier: Topic :: Scientific/Engineering :: Physics
Classifier: Topic :: Software Development :: Libraries :: Python Modules
Requires-Python: >=3.7
Requires-Dist: numpy
